pysteampathprovider/__init__.py
pysteampathprovider/provider.py
PySteamPathProvider-1.3.dist-info/LICENSE
PySteamPathProvider-1.3.dist-info/METADATA
PySteamPathProvider-1.3.dist-info/WHEEL
PySteamPathProvider-1.3.dist-info/top_level.txt
PySteamPathProvider-1.3.dist-info/RECORD
