Metadata-Version: 2.1
Name: PySteamPathProvider
Version: 1.3
Summary: Library used for accessing the installation directories (and app names) given Steam app-ids.
Author: Enderek
License: MIT
Project-URL: source, https://github.com/TheEnderek0/PySteamPathProvider/
Keywords: Steam,Valve,Source Engine
Classifier: Development Status :: 5 - Production/Stable
Classifier: License :: OSI Approved :: MIT License
Classifier: Programming Language :: Python :: 3 :: Only
Classifier: Operating System :: Microsoft :: Windows
Classifier: Operating System :: POSIX :: Linux
Classifier: Topic :: Software Development :: Libraries
Classifier: Topic :: Games/Entertainment
Requires-Python: >=3.8
License-File: LICENSE
Requires-Dist: srctools >=2.4.0
